LICENSE
MANIFEST.in
README.rst
setup.cfg
setup.py
ppy_radix.egg-info/PKG-INFO
ppy_radix.egg-info/SOURCES.txt
ppy_radix.egg-info/dependency_links.txt
ppy_radix.egg-info/top_level.txt
radix/__init__.py
radix/radix.py