Metadata-Version: 1.1
Name: ppy-radix
Version: 0.10.0
Summary: Pure-Python radix tree implementation
Home-page: https://github.com/agaridata/ppy-radix
Author: Agari Engineering
Author-email: eng-team@agari.com
License: BSD
Keywords: radix tree trie python routing networking
Platform: UNKNOWN
Classifier: Intended Audience :: Developers
Classifier: Topic :: Software Development :: Libraries :: Python Modules
Classifier: Topic :: System :: Networking
Classifier: License :: OSI Approved :: BSD License
Classifier: Programming Language :: Python :: 2
Classifier: Programming Language :: Python :: 2.7
Classifier: Programming Language :: Python :: 3
Classifier: Programming Language :: Python :: 3.3
Classifier: Programming Language :: Python :: 3.4
Classifier: Programming Language :: Python :: 3.5
